kit_test/__init__.py
kit_test/_version.py
kit_test/arduino_flash.py
kit_test/arduino_test.py
kit_test/camera_test.py
kit_test/cli.py
kit_test/motor_test.py
kit_test/power_test.py
kit_test/servo_test.py
kit_test/arduino_binaries/__init__.py
kit_test/arduino_binaries/ruggeduino-2.hex
kit_test/arduino_binaries/ruggeduino_test-1.hex
kit_test/hal/__init__.py
kit_test/hal/discovery.py
kit_test/hal/motor_board.py
kit_test/hal/power_board.py
kit_test/hal/serial_wrapper.py
kit_test/hal/servo_board.py
kit_test/hal/utils.py
kit_test/inventory_helpers/__init__.py
kit_test/inventory_helpers/collate_items.py
kit_test/inventory_helpers/collate_tested.py
kit_test/inventory_helpers/empty_boxes.py
sr_kit_test-1.0.0.dist-info/licenses/LICENSE
sr_kit_test-1.0.0.dist-info/METADATA
sr_kit_test-1.0.0.dist-info/WHEEL
sr_kit_test-1.0.0.dist-info/entry_points.txt
sr_kit_test-1.0.0.dist-info/top_level.txt
sr_kit_test-1.0.0.dist-info/RECORD
