Metadata-Version: 2.4
Name: sr-kit-test
Version: 1.0.0
Summary: A collection of test scripts for the Student Robotics v4 kit.
Author-email: Will Barber <wbarber@studentrobotics.org>
Maintainer-email: Student Robotics <kit-team@studentrobotics.org>
License-Expression: MIT
Project-URL: Repository, https://github.com/srobo/kit_test
Classifier: Topic :: Software Development :: Libraries :: Python Modules
Classifier: Programming Language :: Python :: 3
Classifier: Operating System :: OS Independent
Classifier: Development Status :: 4 - Beta
Classifier: Intended Audience :: Developers
Classifier: Typing :: Typed
Requires-Python: >=3.8
License-File: LICENSE
Requires-Dist: pyserial<4,>=3
Requires-Dist: avrdude-windows==7.1.0; sys_platform == "win32"
Requires-Dist: april_vision<4,>=3
Requires-Dist: opencv-python<5,>=4.10
Provides-Extra: dev
Requires-Dist: poethepoet<1,>=0.0.1; extra == "dev"
Requires-Dist: ruff<0.12,>=0.11.0; extra == "dev"
Requires-Dist: mypy==1.9.0; extra == "dev"
Requires-Dist: build; extra == "dev"
Requires-Dist: types-pyserial<4,>=3; extra == "dev"
Provides-Extra: inv
Requires-Dist: sr.tools==2.0.0a1; extra == "inv"
Dynamic: license-file
